locksey/__init__.py
locksey/__main__.py
locksey/config.py
locksey/encrypt.py
locksey/errors.py
locksey/file.py
locksey-0.1.0.dist-info/LICENSE
locksey-0.1.0.dist-info/METADATA
locksey-0.1.0.dist-info/WHEEL
locksey-0.1.0.dist-info/top_level.txt
locksey-0.1.0.dist-info/RECORD
