Metadata-Version: 2.1
Name: locksey
Version: 0.1.0
Summary: Personal CLI utility tool to easily encrypt and decrypt files in a directory.
Home-page: https://github.com/RainingComputers/locksey
Author: RainingComputers
Author-email: vishnu.vish.shankar@gmail.com
Keywords: locksey
Classifier: Programming Language :: Python :: 3
Classifier: License :: OSI Approved :: MIT License
Classifier: Operating System :: OS Independent
Classifier: Development Status :: 3 - Alpha
Classifier: Topic :: Utilities
Requires-Python: >=3.8
License-File: LICENSE
Requires-Dist: cryptography
